zuper_utils_asyncio.pyi
zuper_utils_asyncio.cpython-310-aarch64-linux-gnu.so
zuper_utils_asyncio_z7-7.3.2202161758.dist-info/METADATA
zuper_utils_asyncio_z7-7.3.2202161758.dist-info/WHEEL
zuper_utils_asyncio_z7-7.3.2202161758.dist-info/top_level.txt
zuper_utils_asyncio_z7-7.3.2202161758.dist-info/zip-safe
zuper_utils_asyncio_z7-7.3.2202161758.dist-info/RECORD
