Metadata-Version: 2.1
Name: zuper-utils-asyncio-z7
Version: 7.3.2202161758
Summary: UNKNOWN
Home-page: https://github.com/zupermind/zuper-utils-asyncio
Author: Andrea Censi
Author-email: info@zupermind.com
License: UNKNOWN
Platform: UNKNOWN
Requires-Dist: typing-extensions
Requires-Dist: zuper-commons-z7
Requires-Dist: zuper-typing-z7
Provides-Extra: test
